py_svg_hush-0.2.0.dist-info/METADATA
py_svg_hush-0.2.0.dist-info/WHEEL
py_svg_hush-0.2.0.dist-info/licenses/LICENSE.txt
py_svg_hush/__init__.py
py_svg_hush/__init__.pyi
py_svg_hush/py.typed
py_svg_hush/py_svg_hush.pypy310-pp73-aarch64-linux-gnu.so
py_svg_hush-0.2.0.dist-info/RECORD
